echidna_parade/__main__.py
echidna_parade/campaign.py
echidna_parade/config.py
echidna_parade/echidna.py
echidna_parade-0.2.dist-info/LICENSE
echidna_parade-0.2.dist-info/METADATA
echidna_parade-0.2.dist-info/WHEEL
echidna_parade-0.2.dist-info/entry_points.txt
echidna_parade-0.2.dist-info/top_level.txt
echidna_parade-0.2.dist-info/RECORD
