Metadata-Version: 2.1
Name: echidna-parade
Version: 0.2
Summary: Meta-tool to test a contract with various configs, using Echidna processes
Home-page: https://github.com/crytic/echidna-parade
License: AGPL3
Keywords: echidna smart-contracts testing fuzzing swarm test-diversity
Platform: UNKNOWN
Classifier: Intended Audience :: Developers
Classifier: Development Status :: 4 - Beta
Classifier: Programming Language :: Python :: 3
License-File: LICENSE
Requires-Dist: pyyaml
Requires-Dist: slither-analyzer
Requires-Dist: crytic-compile
Provides-Extra: lint
Requires-Dist: black (==20.8b1) ; extra == 'lint'
Requires-Dist: mypy (==0.790) ; extra == 'lint'
